fixie/__init__.py
fixie/agents/__init__.py
fixie/agents/api.py
fixie/agents/code_shot.py
fixie/agents/code_shot_test.py
fixie/agents/user_storage.py
fixie/agents/user_storage_test.py
fixie/agents/utils.py
fixie/agents/utils_test.py
fixie/client/__init__.py
fixie/client/client.py
fixie/client/client_test.py
fixie/client/console.py
fixie/client/session.py
fixie/constants.py
fixie_ai-0.1.3.dist-info/entry_points.txt
fixie_ai-0.1.3.dist-info/LICENSE
fixie_ai-0.1.3.dist-info/WHEEL
fixie_ai-0.1.3.dist-info/METADATA
fixie_ai-0.1.3.dist-info/RECORD
